pyiacapu/__init__.py
pyiacapu/conceitos.py
pyiacapu/constants.py
pyiacapu/knn.py
pyiacapu/mlp.py
pyiacapu-0.2.4.dist-info/LICENSE
pyiacapu-0.2.4.dist-info/METADATA
pyiacapu-0.2.4.dist-info/WHEEL
pyiacapu-0.2.4.dist-info/top_level.txt
pyiacapu-0.2.4.dist-info/RECORD
